{
    "_id": "1",
    "name": "至善楼",
    "aliases": "1、2、3区 | 公共教学楼",
    "img": "cloud://gluguide-0g65cvsv649006da.676c-gluguide-0g65cvsv649006da-1316857255/学校/楼宇/building_zhishan.jpg",
    "desc": "全校最大的教学楼，含有多媒体教室、电脑机房等教室",
    "latitude": "25.095394",
    "longitude": "110.279427",
    "s_id": 1,
    "c_id": 1,
    "browse": 213
}
{
    "_id": "2",
    "name": "嘉善楼",
    "aliases": "6区 教音 | 设计 | 传媒",
    "img": "cloud://gluguide-0g65cvsv649006da.676c-gluguide-0g65cvsv649006da-1316857255/学校/楼宇/building_jiashan.jpg",
    "desc": "6区\n听说有很多工作室、播音室、练琴房、陶艺室，不过这里的机房巨卡",
    "latitude": "25.096617",
    "longitude": "110.277466",
    "s_id": 2,
    "c_id": 1,
    "browse": 131
}
{
    "_id": "3",
    "name": "彰善楼",
    "aliases": "4区 体育 | 活动中心",
    "img": "cloud://gluguide-0g65cvsv649006da.676c-gluguide-0g65cvsv649006da-1316857255/学校/楼宇/building_zhangshan.jpg",
    "desc": "学生运动的好去处",
    "latitude": "25.097369",
    "longitude": "110.278476",
    "s_id": 3.0,
    "c_id": 1,
    "browse": 147
}
{
    "_id": "4",
    "name": "知善楼",
    "aliases": "8区 行政楼",
    "img": "cloud://gluguide-0g65cvsv649006da.676c-gluguide-0g65cvsv649006da-1316857255/学校/楼宇/building_zhishanlou.jpg",
    "desc": "学校众多机构所在地",
    "latitude": "25.096469",
    "longitude": "110.280638",
    "s_id": 4,
    "c_id": 1,
    "browse": 101
}
{
    "_id": "5",
    "name": "乐善楼",
    "aliases": "后勤部",
    "img": "cloud://gluguide-0g65cvsv649006da.676c-gluguide-0g65cvsv649006da-1316857255/学校/楼宇/building_leshan.jpg",
    "desc": "后勤部所在地",
    "latitude": "25.093916",
    "longitude": "110.278613",
    "s_id": 5,
    "c_id": 1,
    "browse": 83
}
{
    "_id": "6",
    "name": "图书馆A馆区",
    "aliases": "一楼阅览室",
    "img": "cloud://gluguide-0g65cvsv649006da.676c-gluguide-0g65cvsv649006da-1316857255/学校/图书馆/library_A.jpg",
    "desc": "距离宿舍最近的阅览室，不过电脑声音很吵就是了",
    "latitude": "25.095037",
    "longitude": "110.279283",
    "s_id": 6,
    "c_id": 2,
    "browse": 111
}
{
    "_id": "7",
    "name": "图书馆B馆区",
    "aliases": "一楼藏书室",
    "img": "cloud://gluguide-0g65cvsv649006da.676c-gluguide-0g65cvsv649006da-1316857255/学校/图书馆/library_B.jpg",
    "desc": "看书的好地方",
    "latitude": "25.095637",
    "longitude": "110.279283",
    "s_id": 7,
    "c_id": 2,
    "browse": 61
}
{
    "_id": "8",
    "name": "图书馆C馆区",
    "aliases": "一二楼藏书三楼阅览室",
    "img": "cloud://gluguide-0g65cvsv649006da.676c-gluguide-0g65cvsv649006da-1316857255/学校/图书馆/library_C.jpg",
    "desc": "一二三楼内部有楼梯连通",
    "latitude": "25.09612",
    "longitude": "110.279283",
    "s_id": 8,
    "c_id": 2,
    "browse": 48
}
{
    "_id": "9",
    "name": "语言文学学院",
    "aliases": "",
    "img": "cloud://gluguide-0g65cvsv649006da.676c-gluguide-0g65cvsv649006da-1316857255/学校/二级学院/school_yuyan.jpg",
    "desc": "至善楼2区西侧一楼",
    "latitude": "25.094589",
    "longitude": "110.279256",
    "s_id": 9,
    "c_id": 3,
    "browse": 55
}
{
    "_id": "10",
    "name": "商贸与法律学院",
    "aliases": "",
    "img": "cloud://gluguide-0g65cvsv649006da.676c-gluguide-0g65cvsv649006da-1316857255/学校/二级学院/school_shangfa.jpg",
    "desc": "至善楼3区一、二楼",
    "latitude": "25.096078",
    "longitude": "110.279825",
    "s_id": 10,
    "c_id": 3,
    "browse": 40
}
{
    "_id": "11",
    "name": "经济与管理学院",
    "aliases": "",
    "img": "cloud://gluguide-0g65cvsv649006da.676c-gluguide-0g65cvsv649006da-1316857255/学校/二级学院/school_jingji.jpg",
    "desc": "至善楼3区四、五楼",
    "latitude": "25.096256",
    "longitude": "110.279742",
    "s_id": 11,
    "c_id": 3,
    "browse": 39
}
{
    "_id": "12",
    "name": "教育与音乐学院",
    "aliases": "",
    "img": "cloud://gluguide-0g65cvsv649006da.676c-gluguide-0g65cvsv649006da-1316857255/学校/二级学院/school_jiaoyin.jpg",
    "desc": "嘉善楼东侧一楼",
    "latitude": "25.096437",
    "longitude": "110.27716",
    "s_id": 12,
    "c_id": 3,
    "browse": 28
}
{
    "_id": "13",
    "name": "理工学院",
    "aliases": "",
    "img": "cloud://gluguide-0g65cvsv649006da.676c-gluguide-0g65cvsv649006da-1316857255/学校/二级学院/school_ligong.jpg",
    "desc": "至善楼2区东侧一楼",
    "latitude": "25.0944",
    "longitude": "110.279763",
    "s_id": 13,
    "c_id": 3,
    "browse": 70
}
{
    "_id": "14",
    "name": "设计学院",
    "aliases": "",
    "img": "cloud://gluguide-0g65cvsv649006da.676c-gluguide-0g65cvsv649006da-1316857255/学校/二级学院/school_sheji.jpg",
    "desc": "嘉善楼西侧一楼",
    "latitude": "25.096334",
    "longitude": "110.276336",
    "s_id": 14,
    "c_id": 3,
    "browse": 19
}
{
    "_id": "15",
    "name": "体育与健康学院",
    "aliases": "",
    "img": "cloud://gluguide-0g65cvsv649006da.676c-gluguide-0g65cvsv649006da-1316857255/学校/二级学院/school_tiyu.jpg",
    "desc": "彰善楼东侧二楼",
    "latitude": "25.097503",
    "longitude": "110.278562",
    "s_id": 15,
    "c_id": 3,
    "browse": 23
}
{
    "_id": "16",
    "name": "传媒学院",
    "aliases": "",
    "img": "cloud://gluguide-0g65cvsv649006da.676c-gluguide-0g65cvsv649006da-1316857255/学校/二级学院/school_chuanmei.jpg",
    "desc": "嘉善楼最西侧一楼",
    "latitude": "25.096205",
    "longitude": "110.275699",
    "s_id": 16,
    "c_id": 3,
    "browse": 21
}
{
    "_id": "17",
    "name": "东门",
    "aliases": "学校正大门",
    "img": "cloud://gluguide-0g65cvsv649006da.676c-gluguide-0g65cvsv649006da-1316857255/学校/校门/schoolgate_dongmen.jpg",
    "desc": "学校正大门\n可以通行行人和车辆",
    "latitude": "25.095321",
    "longitude": "110.280392",
    "s_id": 17,
    "c_id": 4,
    "browse": 109
}
{
    "_id": "18",
    "name": "北门",
    "aliases": "学校侧门",
    "img": "cloud://gluguide-0g65cvsv649006da.676c-gluguide-0g65cvsv649006da-1316857255/学校/校门/schoolgate_beimen.jpeg",
    "desc": "学校侧门（原大门）\n只能通行行人，不能通行车辆",
    "latitude": "25.097448",
    "longitude": "110.277449",
    "s_id": 18,
    "c_id": 4,
    "browse": 96
}
{
    "_id": "19",
    "name": "弘善讲堂",
    "aliases": "大讲堂",
    "img": "cloud://gluguide-0g65cvsv649006da.676c-gluguide-0g65cvsv649006da-1316857255/学校/会议厅/meetingroom_hongshan.jpg",
    "desc": "学校最大的会议厅",
    "latitude": "25.096059",
    "longitude": "110.276561",
    "s_id": 19,
    "c_id": 5,
    "browse": 55
}
{
    "_id": "20",
    "name": "至善讲堂",
    "aliases": "",
    "img": "cloud://gluguide-0g65cvsv649006da.676c-gluguide-0g65cvsv649006da-1316857255/学校/会议厅/meetingroom_zhishan.jpg",
    "desc": "至善楼中部西侧一楼\n小小会议厅，这里经常举办各种活动",
    "latitude": "25.095393",
    "longitude": "110.278823",
    "s_id": 20,
    "c_id": 5,
    "browse": 46
}
{
    "_id": "21",
    "name": "田径场",
    "aliases": "跑道",
    "img": "cloud://gluguide-0g65cvsv649006da.676c-gluguide-0g65cvsv649006da-1316857255/学校/体育场馆/sport_tianjing.jpg",
    "desc": "学生跑步的好去处",
    "latitude": "25.097907",
    "longitude": "110.28037",
    "s_id": 21,
    "c_id": 6,
    "browse": 31
}
{
    "_id": "22",
    "name": "篮球场",
    "aliases": "",
    "img": "cloud://gluguide-0g65cvsv649006da.676c-gluguide-0g65cvsv649006da-1316857255/学校/体育场馆/sport_basketball.jpg",
    "desc": "学生打球的好去处",
    "latitude": "25.097452",
    "longitude": "110.279299",
    "s_id": 22,
    "c_id": 6,
    "browse": 16
}
{
    "_id": "23",
    "name": "排球场",
    "aliases": "",
    "img": "cloud://gluguide-0g65cvsv649006da.676c-gluguide-0g65cvsv649006da-1316857255/学校/体育场馆/sport_volleyball.jpg",
    "desc": "学生打排球的好去处",
    "latitude": "25.098016",
    "longitude": "110.279460",
    "s_id": 23,
    "c_id": 6,
    "browse": 14
}
{
    "_id": "24",
    "name": "小足球场",
    "aliases": "",
    "img": "cloud://gluguide-0g65cvsv649006da.676c-gluguide-0g65cvsv649006da-1316857255/学校/体育场馆/sport_football2.jpg",
    "desc": "学生踢球的好去处",
    "latitude": "25.098033",
    "longitude": "110.279207",
    "s_id": 24,
    "c_id": 6,
    "browse": 14
}
{
    "_id": "25",
    "name": "户外拓展基地",
    "aliases": "攀岩设施",
    "img": "cloud://gluguide-0g65cvsv649006da.676c-gluguide-0g65cvsv649006da-1316857255/学校/体育场馆/sport_climbing.jpg",
    "desc": "学生攀岩的。。。上课场所",
    "latitude": "25.097654",
    "longitude": "110.278788",
    "s_id": 25,
    "c_id": 6,
    "browse": 20
}
{
    "_id": "26",
    "name": "活动中心",
    "aliases": "室内羽毛球场、篮球场",
    "img": "cloud://gluguide-0g65cvsv649006da.676c-gluguide-0g65cvsv649006da-1316857255/学校/体育场馆/sport_indoor.jpg",
    "desc": "学生打羽毛球的好去处\n就是老是抢不到场（恼）",
    "latitude": "25.0975",
    "longitude": "110.278287",
    "s_id": 26,
    "c_id": 6,
    "browse": 11
}
{
    "_id": "27",
    "name": "至善广场",
    "aliases": "大阶梯",
    "img": "cloud://gluguide-0g65cvsv649006da.676c-gluguide-0g65cvsv649006da-1316857255/学校/广场/square_zhishan.jpg",
    "desc": "这里有宽宽的大阶梯，是拍集体照的好地方",
    "latitude": "25.095328",
    "longitude": "110.27991",
    "s_id": 27,
    "c_id": 7,
    "browse": 9
}
{
    "_id": "28",
    "name": "乐善广场",
    "aliases": "食堂广场",
    "img": "cloud://gluguide-0g65cvsv649006da.676c-gluguide-0g65cvsv649006da-1316857255/学校/广场/square_leshsan.jpg",
    "desc": "这里经常举办各类社团活动、献血活动，以及早早的升旗",
    "latitude": "25.093364",
    "longitude": "110.278744",
    "s_id": 28,
    "c_id": 7,
    "browse": 28
}
{
    "_id": "29",
    "name": "弘善广场",
    "aliases": "",
    "img": "cloud://gluguide-0g65cvsv649006da.676c-gluguide-0g65cvsv649006da-1316857255/学校/广场/square_hongshan.jpg",
    "desc": "每次弘善讲堂开会，这里都会排满密密麻麻的人",
    "latitude": "25.096035",
    "longitude": "110.276883",
    "s_id": 29,
    "c_id": 7,
    "browse": 13
}
{
    "_id": "30",
    "name": "聚善广场",
    "aliases": "停车场",
    "img": "cloud://gluguide-0g65cvsv649006da.676c-gluguide-0g65cvsv649006da-1316857255/学校/广场/square_jushan.jpg",
    "desc": "学生们经常在这里练滑板",
    "latitude": "25.096726",
    "longitude": "110.279112",
    "s_id": 30,
    "c_id": 7,
    "browse": 11
}
{
    "_id": "31",
    "name": "蓄善池",
    "aliases": "",
    "img": "cloud://gluguide-0g65cvsv649006da.676c-gluguide-0g65cvsv649006da-1316857255/学校/风景/scenery_xushan.jpg",
    "desc": "小小池塘，一方天地",
    "latitude": "25.095757",
    "longitude": "110.280052",
    "s_id": 31,
    "c_id": 8,
    "browse": 13
}
{
    "_id": "32",
    "name": "育善林",
    "aliases": "小树林",
    "img": "cloud://gluguide-0g65cvsv649006da.676c-gluguide-0g65cvsv649006da-1316857255/学校/风景/scenery_yushan.jpg",
    "desc": "枝繁叶茂，清新秀丽，学生往来，小心有蛇",
    "latitude": "25.095712",
    "longitude": "110.277886",
    "s_id": 32,
    "c_id": 8,
    "browse": 9
}
{
    "_id": "33",
    "name": "假山石榭",
    "aliases": "",
    "img": "cloud://gluguide-0g65cvsv649006da.676c-gluguide-0g65cvsv649006da-1316857255/学校/风景/scenery_jiashan.jpg",
    "desc": "学生们经常在这里拍照或者录视频",
    "latitude": "25.094892",
    "longitude": "110.279911",
    "s_id": 33,
    "c_id": 8,
    "browse": 11
}
{
    "_id": "34",
    "name": "石砖长廊",
    "aliases": "",
    "img": "cloud://gluguide-0g65cvsv649006da.676c-gluguide-0g65cvsv649006da-1316857255/学校/风景/scenery_shizhuan.jpg",
    "desc": "红砖长椅，石板道路",
    "latitude": "25.094066",
    "longitude": "110.280193",
    "s_id": 34,
    "c_id": 8,
    "browse": 17
}
{
    "_id": "35",
    "name": "党建主题长廊",
    "aliases": "",
    "img": "cloud://gluguide-0g65cvsv649006da.676c-gluguide-0g65cvsv649006da-1316857255/学校/风景/scenery_dangjian.jpg",
    "desc": "红色精神永存",
    "latitude": "25.096783",
    "longitude": "110.277940",
    "s_id": 35,
    "c_id": 8,
    "browse": 7
}
{
    "_id": "36",
    "name": "校史大厅",
    "aliases": "",
    "img": "cloud://gluguide-0g65cvsv649006da.676c-gluguide-0g65cvsv649006da-1316857255/学校/风景/scenery_xiaoshi.jpg",
    "desc": "记载了数十载桂院历程",
    "latitude": "25.095380",
    "longitude": "110.279483",
    "s_id": 36,
    "c_id": 8,
    "browse": 14
}
{
    "_id": "37",
    "name": "生态文明教育园地",
    "aliases": "",
    "img": "cloud://gluguide-0g65cvsv649006da.676c-gluguide-0g65cvsv649006da-1316857255/学校/风景/scenery_shengtai.jpg",
    "desc": "小小园地，风景秀丽",
    "latitude": "25.095100",
    "longitude": "110.277053",
    "s_id": 37,
    "c_id": 8,
    "browse": 10
}
{
    "_id": "38",
    "name": "乐善食府",
    "aliases": "食堂",
    "img": "cloud://gluguide-0g65cvsv649006da.676c-gluguide-0g65cvsv649006da-1316857255/学校/美食/delicious_leshan.jpg",
    "desc": "冲呀！干饭呀！",
    "latitude": "25.093691",
    "longitude": "110.278181",
    "s_id": 38,
    "c_id": 9,
    "browse": 45
}
{
    "_id": "39",
    "name": "美食后街",
    "aliases": "",
    "img": "cloud://gluguide-0g65cvsv649006da.676c-gluguide-0g65cvsv649006da-1316857255/学校/美食/delicious_houjie.jpg",
    "desc": "学生们的美食天地",
    "latitude": "25.093228",
    "longitude": "110.278048",
    "s_id": 39,
    "c_id": 9,
    "browse": 39
}
{
    "_id": "40",
    "name": "蜜雪冰城",
    "aliases": "",
    "img": "cloud://gluguide-0g65cvsv649006da.676c-gluguide-0g65cvsv649006da-1316857255/学校/美食/delicious_mixue.jpg",
    "desc": "你爱我 我爱你 蜜雪冰城甜蜜蜜",
    "latitude": "25.094037",
    "longitude": "110.278461",
    "s_id": 40,
    "c_id": 9,
    "browse": 49
}
{
    "_id": "41",
    "name": "卫生所",
    "aliases": "医务室",
    "img": "cloud://gluguide-0g65cvsv649006da.676c-gluguide-0g65cvsv649006da-1316857255/学校/学生服务/student_weisheng.jpg",
    "desc": "记得戴口罩哦，如果去医院记得弄清报销材料和流程",
    "latitude": "25.094901",
    "longitude": "110.277143",
    "s_id": 41,
    "c_id": 10,
    "browse": 24
}
{
    "_id": "42",
    "name": "大学生心理健康与咨询中心",
    "aliases": "",
    "img": "cloud://gluguide-0g65cvsv649006da.676c-gluguide-0g65cvsv649006da-1316857255/学校/学生服务/student_xinli.jpg",
    "desc": "提供心理咨询等服务，需要提前预约",
    "latitude": "25.094914",
    "longitude": "110.276330",
    "s_id": 42,
    "c_id": 10,
    "browse": 27
}
{
    "_id": "43",
    "name": "大学生创新创业实践基地",
    "aliases": "",
    "img": "cloud://gluguide-0g65cvsv649006da.676c-gluguide-0g65cvsv649006da-1316857255/学校/学生服务/student_chuangye.jpg",
    "desc": "这里曾经非常热闹",
    "latitude": "25.094640",
    "longitude": "110.277248",
    "s_id": 43,
    "c_id": 10,
    "browse": 15
}
{
    "_id": "44",
    "name": "财务处充值中心",
    "aliases": "水、电充值",
    "img": "cloud://gluguide-0g65cvsv649006da.676c-gluguide-0g65cvsv649006da-1316857255/学校/学生服务/student_chongzhi.jpg",
    "desc": "乐善楼二楼\n直饮水、电卡充值处、电卡圈存机",
    "latitude": "25.093913",
    "longitude": "110.278747",
    "s_id": 44,
    "c_id": 10,
    "browse": 27
}
{
    "_id": "45",
    "name": "校内快递点",
    "aliases": "点击查看快递点详情",
    "img": "cloud://gluguide-0g65cvsv649006da.676c-gluguide-0g65cvsv649006da-1316857255/学校/生活服务/life_kuaidi.jpg",
    "desc": "百世 | 圆通 | 申通 | 京东 | 中通 | 韵达 | 顺丰",
    "latitude": "25.091247",
    "longitude": "110.277722",
    "s_id": 45,
    "c_id": 11,
    "browse": 18
}
{
    "_id": "46",
    "name": "校外快递点",
    "aliases": "邮政快递",
    "img": "cloud://gluguide-0g65cvsv649006da.676c-gluguide-0g65cvsv649006da-1316857255/学校/生活服务/life_youzheng.jpg",
    "desc": "北门马路对面西侧加州旅馆旁，好远，建议快递走其他家",
    "latitude": "25.09827",
    "longitude": "110.278491",
    "s_id": 46,
    "c_id": 11,
    "browse": 15
}
{
    "_id": "47",
    "name": "宇家超市",
    "aliases": "",
    "img": "cloud://gluguide-0g65cvsv649006da.676c-gluguide-0g65cvsv649006da-1316857255/学校/生活服务/life_yujia.jpg",
    "desc": "食堂旁一家平凡的超市，学生一般都去那里买东西",
    "latitude": "25.093817",
    "longitude": "110.278485",
    "s_id": 47,
    "c_id": 11,
    "browse": 14
}
{
    "_id": "48",
    "name": "鑫源超市",
    "aliases": "",
    "img": "cloud://gluguide-0g65cvsv649006da.676c-gluguide-0g65cvsv649006da-1316857255/学校/生活服务/life_xinyuan.jpg",
    "desc": "一家平凡的超市，学生一般都去那里买东西",
    "latitude": "25.093849",
    "longitude": "110.278742",
    "s_id": 48,
    "c_id": 11,
    "browse": 13
}
{
    "_id": "49",
    "name": "理发店",
    "aliases": "",
    "img": "cloud://gluguide-0g65cvsv649006da.676c-gluguide-0g65cvsv649006da-1316857255/学校/生活服务/life_lifa.jpg",
    "desc": "一家平凡的理发店，我室友的头发在那被理废一次",
    "latitude": "25.094065",
    "longitude": "110.278362",
    "s_id": 49,
    "c_id": 11,
    "browse": 11
}
{
    "_id": "50",
    "name": "锁店",
    "aliases": "",
    "img": "cloud://gluguide-0g65cvsv649006da.676c-gluguide-0g65cvsv649006da-1316857255/学校/生活服务/life_suo.jpg",
    "desc": "一家平凡的锁店，学生配钥匙一般都去那里配",
    "latitude": "25.094649",
    "longitude": "110.276912",
    "s_id": 50,
    "c_id": 11,
    "browse": 17
}
{
    "_id": "51",
    "name": "康鑫大药房",
    "aliases": "药店",
    "img": "cloud://gluguide-0g65cvsv649006da.676c-gluguide-0g65cvsv649006da-1316857255/学校/生活服务/life_yaodian.jpg",
    "desc": "一家平凡的药店，学生经常去那里称称自己的体重",
    "latitude": "25.093974",
    "longitude": "110.278732",
    "s_id": 51,
    "c_id": 11,
    "browse": 12
}
{
    "_id": "52",
    "name": "象山家苑",
    "aliases": "东一女生宿舍楼",
    "img": "cloud://gluguide-0g65cvsv649006da.676c-gluguide-0g65cvsv649006da-1316857255/学校/宿舍公寓/dormitory_xiangshan.jpg",
    "desc": "食堂就在对面，干饭干饭",
    "latitude": "25.093689",
    "longitude": "110.279373",
    "s_id": 52,
    "c_id": 12,
    "browse": 36
}
{
    "_id": "53",
    "name": "叠彩家苑",
    "aliases": "东二男生宿舍楼",
    "img": "cloud://gluguide-0g65cvsv649006da.676c-gluguide-0g65cvsv649006da-1316857255/学校/宿舍公寓/dormitory_diecai.jpg",
    "desc": "这栋是男生宿舍楼，对面也是男生宿舍楼",
    "latitude": "25.092834",
    "longitude": "110.279102",
    "s_id": 53,
    "c_id": 12,
    "browse": 21
}
{
    "_id": "54",
    "name": "伏波家苑",
    "aliases": "东三女生宿舍楼",
    "img": "cloud://gluguide-0g65cvsv649006da.676c-gluguide-0g65cvsv649006da-1316857255/学校/宿舍公寓/dormitory_fubo.jpg",
    "desc": "快递点就在斜对面",
    "latitude": "25.092030",
    "longitude": "110.278764",
    "s_id": 54,
    "c_id": 12,
    "browse": 33
}
{
    "_id": "55",
    "name": "独秀家苑",
    "aliases": "东四女生宿舍楼",
    "img": "cloud://gluguide-0g65cvsv649006da.676c-gluguide-0g65cvsv649006da-1316857255/学校/宿舍公寓/dormitory_duxiu.jpg",
    "desc": "快递点就在对面",
    "latitude": "25.091359",
    "longitude": "110.278395",
    "s_id": 55.0,
    "c_id": 12,
    "browse": 68
}
{
    "_id": "56",
    "name": "七星家苑",
    "aliases": "西一男生宿舍楼",
    "img": "cloud://gluguide-0g65cvsv649006da.676c-gluguide-0g65cvsv649006da-1316857255/学校/宿舍公寓/dormitory_qixing.jpg",
    "desc": "曾经的鸳鸯楼",
    "latitude": "25.093044",
    "longitude": "110.278562",
    "s_id": 56,
    "c_id": 12,
    "browse": 49
}
{
    "_id": "57",
    "name": "芦笛家苑",
    "aliases": "西二女生宿舍楼",
    "img": "cloud://gluguide-0g65cvsv649006da.676c-gluguide-0g65cvsv649006da-1316857255/学校/宿舍公寓/dormitory_ludi.jpg",
    "desc": "快递点就在旁边",
    "latitude": "25.092214",
    "longitude": "110.278217",
    "s_id": 57,
    "c_id": 12,
    "browse": 21
}
{
    "_id": "58",
    "name": "榕湖家苑",
    "aliases": "女生宿舍楼",
    "img": "cloud://gluguide-0g65cvsv649006da.676c-gluguide-0g65cvsv649006da-1316857255/学校/宿舍公寓/dormitory_ronghu.jpg",
    "desc": "听说是10人间的女生宿舍楼",
    "latitude": "25.095623",
    "longitude": "110.275874",
    "s_id": 58,
    "c_id": 12,
    "browse": 25
}
{
    "_id": "59",
    "name": "杉湖家苑",
    "aliases": "女生宿舍楼",
    "img": "cloud://gluguide-0g65cvsv649006da.676c-gluguide-0g65cvsv649006da-1316857255/学校/宿舍公寓/dormitory_shanhu.jpg",
    "desc": "一栋高高的女生宿舍楼",
    "latitude": "25.094923",
    "longitude": "110.276556",
    "s_id": 59,
    "c_id": 12,
    "browse": 18
}
{
    "_id": "60",
    "name": "桂湖家苑",
    "aliases": "教职工宿舍楼",
    "img": "cloud://gluguide-0g65cvsv649006da.676c-gluguide-0g65cvsv649006da-1316857255/学校/宿舍公寓/dormitory_guihu.jpg",
    "desc": "",
    "latitude": "25.094652",
    "longitude": "110.276902",
    "s_id": 60,
    "c_id": 12,
    "browse": 28
}
{
    "_id": "61",
    "name": "南溪家苑",
    "aliases": "女生宿舍楼",
    "img": "cloud://gluguide-0g65cvsv649006da.676c-gluguide-0g65cvsv649006da-1316857255/学校/宿舍公寓/dormitory_nanxi.jpg",
    "desc": "新建学生宿舍楼听说有高贵的二人间和电梯",
    "latitude": "25.090311",
    "longitude": "110.277327",
    "s_id": 61,
    "c_id": 12,
    "browse": 58
}
{
    "_id": "62",
    "name": "木龙湖家苑",
    "aliases": "男生宿舍楼",
    "img": "cloud://gluguide-0g65cvsv649006da.676c-gluguide-0g65cvsv649006da-1316857255/学校/宿舍公寓/dormitory_mulong.jpg",
    "desc": "新建学生宿舍楼听说有高贵的二人间和电梯",
    "latitude": "25.093952",
    "longitude": "110.274824",
    "s_id": 62,
    "c_id": 12,
    "browse": 37
}
{
    "_id": "63",
    "name": "考研教室",
    "aliases": "",
    "img": "cloud://gluguide-0g65cvsv649006da.676c-gluguide-0g65cvsv649006da-1316857255/学校/其他/other_kaoyan.jpg",
    "desc": "至善楼中部西侧二楼\n向考研学子致敬！",
    "latitude": "25.095393",
    "longitude": "110.278864",
    "s_id": 63,
    "c_id": 13,
    "browse": 32
}
{
    "_id": "64",
    "name": "风雨棚",
    "aliases": "",
    "img": "cloud://gluguide-0g65cvsv649006da.676c-gluguide-0g65cvsv649006da-1316857255/学校/其他/other_fengyupeng.jpg",
    "desc": "学生们经常在那里举办活动或者躲雨",
    "latitude": "25.097778",
    "longitude": "110.279699",
    "s_id": 64,
    "c_id": 13,
    "browse": 16
}
{
    "_id": "65",
    "name": "益世茶苑",
    "aliases": "大益茶室",
    "img": "cloud://gluguide-0g65cvsv649006da.676c-gluguide-0g65cvsv649006da-1316857255/学校/其他/other_dayi.jpg",
    "desc": "乐善楼二楼\n不妨静下心来，品一杯好茶",
    "latitude": "25.093834",
    "longitude": "110.278638",
    "s_id": 65,
    "c_id": 13,
    "browse": 18
}
{
    "_id": "66",
    "name": "独秀书房",
    "aliases": "",
    "img": "cloud://gluguide-0g65cvsv649006da.676c-gluguide-0g65cvsv649006da-1316857255/学校/其他/other_duxiu.jpg",
    "desc": "清幽淡雅，是个读书的好地方",
    "latitude": "25.095045",
    "longitude": "110.276931",
    "s_id": 66,
    "c_id": 13,
    "browse": 16
}
{
    "_id": "67",
    "name": "善学堂",
    "aliases": "",
    "img": "cloud://gluguide-0g65cvsv649006da.676c-gluguide-0g65cvsv649006da-1316857255/学校/其他/other_shanxue.jpg",
    "desc": "至善楼3区四楼\n一块学习小天地",
    "latitude": "25.096446",
    "longitude": "110.279758",
    "s_id": 67,
    "c_id": 13,
    "browse": 21
}
{
    "_id": "68",
    "name": "公交车站",
    "aliases": "K96站台",
    "img": "cloud://gluguide-0g65cvsv649006da.676c-gluguide-0g65cvsv649006da-1316857255/学校/其他/other_busstation.png",
    "desc": "东校门旁小小车站 承载着学生们的大学生活",
    "latitude": "25.094681",
    "longitude": "110.280808",
    "s_id": 68,
    "c_id": 13,
    "browse": 24
}
{
    "_id": "69",
    "name": "教材领取处",
    "aliases": "领书处",
    "img": "cloud://gluguide-0g65cvsv649006da.676c-gluguide-0g65cvsv649006da-1316857255/学校/其他/other_lingshu.jpg",
    "desc": "榕湖家苑对面\n学期伊始，这里都挤满了学生、书本和高贵的小推车",
    "latitude": "25.095193",
    "longitude": "110.276211",
    "s_id": 69,
    "c_id": 13,
    "browse": 30
}
{
    "_id": "70",
    "name": "阿莲健身",
    "aliases": "",
    "img": "cloud://gluguide-0g65cvsv649006da.676c-gluguide-0g65cvsv649006da-1316857255/学校/其他/other_alian.jpg",
    "desc": "彰善楼一楼\n学生健身的好去处",
    "latitude": "25.097218",
    "longitude": "110.278263",
    "s_id": 70,
    "c_id": 13,
    "browse": 16
}